LICENSE
MANIFEST.in
README.rst
changelog.rst
setup.py
gserver/__init__.py
gserver/content_types.py
gserver/exceptions.py
gserver/request.py
gserver/routes.py
gserver/wsgi.py
gserver.egg-info/PKG-INFO
gserver.egg-info/SOURCES.txt
gserver.egg-info/dependency_links.txt
gserver.egg-info/requires.txt
gserver.egg-info/top_level.txt