Metadata-Version: 1.1
Name: gserver
Version: 0.2.0
Summary: Simple wrapper around gevent's wsgi server.Adds simple regex routing, error handling, and json/jsonp handling.
Home-page: http://pypi.python.org/pypi/gserver
Author: Justin Wilson
Author-email: justinwilson1@gmail.com
License: Simplified BSD
Platform: UNKNOWN
Classifier: Development Status :: 4 - Beta
Classifier: Topic :: Utilities
Classifier: License :: OSI Approved :: BSD License
